LICENSE
MANIFEST.in
README.md
setup.py
src/scrapy_scheduler_rabbitmq/__init__.py
src/scrapy_scheduler_rabbitmq/connection.py
src/scrapy_scheduler_rabbitmq/middleware.py
src/scrapy_scheduler_rabbitmq/picklecompat.py
src/scrapy_scheduler_rabbitmq/pipelines.py
src/scrapy_scheduler_rabbitmq/queue.py
src/scrapy_scheduler_rabbitmq/scheduler.py
src/scrapy_scheduler_rabbitmq/spiders.py
src/scrapy_scheduler_rabbitmq.egg-info/PKG-INFO
src/scrapy_scheduler_rabbitmq.egg-info/SOURCES.txt
src/scrapy_scheduler_rabbitmq.egg-info/dependency_links.txt
src/scrapy_scheduler_rabbitmq.egg-info/requires.txt
src/scrapy_scheduler_rabbitmq.egg-info/top_level.txt