Metadata-Version: 2.1
Name: scrapy-scheduler-rabbitmq
Version: 1.1.9
Summary: Rabbitmq for Scrapy Distributed scraping
Home-page: https://github.com/bigkennel/scrapy-scheduler-rabbitmq
Author: sunny5156
Author-email: sunny5156@qq.com
License: MIT
Platform: UNKNOWN
License-File: LICENSE
